SamplingAlgo/__init__.py
SamplingAlgo/metropolis_hastings.py
tests/__init__.py
tests/test_metropolis_hastings.py
SamplingAlgo-0.1.1.dist-info/LICENSE.txt
SamplingAlgo-0.1.1.dist-info/METADATA
SamplingAlgo-0.1.1.dist-info/WHEEL
SamplingAlgo-0.1.1.dist-info/top_level.txt
SamplingAlgo-0.1.1.dist-info/RECORD
